fileactivityhandler/__init__.py
fileactivityhandler-0.0.1.post1.dist-info/LICENSE.md
fileactivityhandler-0.0.1.post1.dist-info/METADATA
fileactivityhandler-0.0.1.post1.dist-info/WHEEL
fileactivityhandler-0.0.1.post1.dist-info/top_level.txt
fileactivityhandler-0.0.1.post1.dist-info/RECORD
