Metadata-Version: 2.1
Name: fileactivityhandler
Version: 0.0.1.R1
Summary: A module to Handle all file / directory activities for automation
Home-page: UNKNOWN
Author: Vikas Bhaskar Vooradi
Author-email: vikasvooradi.devs@gmail.com
License: MIT
Keywords: fileHandling,Automation,fileActivityHandler,setuptools,development
Platform: UNKNOWN
Classifier: Development Status :: 3 - Alpha
Classifier: Intended Audience :: Developers
Classifier: Topic :: Software Development :: Build Tools
Classifier: Operating System :: OS Independent
Classifier: License :: OSI Approved :: MIT License
Classifier: Programming Language :: Python :: 3
Requires-Python: >=3
License-File: LICENSE.md
